setup.py
pbdist/Binomial.py
pbdist/Gaussian.py
pbdist/General.py
pbdist/__init__.py
pbdist.egg-info/PKG-INFO
pbdist.egg-info/SOURCES.txt
pbdist.egg-info/dependency_links.txt
pbdist.egg-info/not-zip-safe
pbdist.egg-info/top_level.txt