Metadata-Version: 1.0
Name: pbdist
Version: 1.0
Summary: Gaussian distribution
Home-page: UNKNOWN
Author: Charitha
Author-email: rsreecharitha@gmail.com
License: UNKNOWN
Platform: UNKNOWN
